RLNEK_tests/__init__.py
rlnek/Module_0A.py
rlnek/Module_0B.py
rlnek/Module_0C.py
rlnek/Module_1.py
rlnek/Module_2.py
rlnek/NT_Optimization.py
rlnek/__init__.py
rlnek/__main__.py
RLNEK-1.0.7.dist-info/METADATA
RLNEK-1.0.7.dist-info/WHEEL
RLNEK-1.0.7.dist-info/license.txt
RLNEK-1.0.7.dist-info/top_level.txt
RLNEK-1.0.7.dist-info/RECORD
