Metadata-Version: 2.1
Name: RLNEK
Version: 1.0.7
Summary: RLNEK is a package to analyze data taken from Trackmate on receptor-ligand kinetics. GitHub: https://github.com/zrollins/RLNEK
Home-page: https://github.com/zrollins/RLNEK
Author: Allison Chan & Zachary Rollins
Author-email: awlchan@ucdavis.edu
License: GNU
Platform: UNKNOWN
Classifier: Programming Language :: Python :: 3
Classifier: Programming Language :: Python :: 3.7
Requires-Dist: pandas (>=1.3.5)
Requires-Dist: numpy (>=1.21.0)
Requires-Dist: scipy (>=1.4.0)
Requires-Dist: matplotlib (>=3.1.0)
